django_paynova
