Metadata-Version: 1.1
Name: django-paynova
Version: 0.1.4
Summary: Python client for Paynova's API. For Django framework.
Home-page: https://github.com/akolpakov/django-paynova
Author: Andrey Kolpakov
Author-email: aakolpakov@gmail.com
License: MIT
Keywords: Paynova API client python django
Platform: UNKNOWN
Classifier: Development Status :: 4 - Beta
Classifier: Intended Audience :: Developers
Classifier: License :: OSI Approved :: MIT License
Classifier: Natural Language :: English
Classifier: Operating System :: Unix
Classifier: Programming Language :: Python :: 2.7
Classifier: Programming Language :: Python :: 3.4
Classifier: Programming Language :: Python :: Implementation :: PyPy
Classifier: Operating System :: OS Independent
